example/__init__.py
example/example.py
tippie-1.0.1.dist-info/METADATA
tippie-1.0.1.dist-info/WHEEL
tippie-1.0.1.dist-info/entry_points.txt
tippie-1.0.1.dist-info/top_level.txt
tippie-1.0.1.dist-info/RECORD
