Metadata-Version: 2.1
Name: tippie
Version: 1.0.1
Summary: you do not have to bother type hinting in python from now on, tippie will take care of it :)
Home-page: https://github.com/aryan-debug/tippie
Author: Aryan Arora
Author-email: aryanarora232004@gmail.com
License: UNKNOWN
Project-URL: Music Player, https://github.com/aryan-debug/Music_Player
Project-URL: Chess Game, https://github.com/aryan-debug/chess_game
Platform: UNKNOWN
Classifier: Programming Language :: Python :: 3
Classifier: Operating System :: OS Independent
Requires-Python: >=3.6
